djspoofer/__init__.py
djspoofer/admin.py
djspoofer/apps.py
djspoofer/backends.py
djspoofer/clients.py
djspoofer/commands.py
djspoofer/connections.py
djspoofer/const.py
djspoofer/dictionary.py
djspoofer/exceptions.py
djspoofer/management/__init__.py
djspoofer/management/commands/__init__.py
djspoofer/management/commands/djspoofer_add_rotating_proxy.py
djspoofer/management/commands/djspoofer_all_fingerprints.py
djspoofer/management/commands/djspoofer_create_desktop_fingerprints.py
djspoofer/management/commands/djspoofer_generate_proxy_csv.py
djspoofer/management/commands/djspoofer_init.py
djspoofer/management/commands/djspoofer_reset.py
djspoofer/management/commands/djspoofer_test_proxies.py
djspoofer/management/commands/h2_fingerprint.py
djspoofer/management/commands/howsmyssl_check.py
djspoofer/management/commands/incolumitas_ip_fingerprint.py
djspoofer/management/commands/incolumitas_tcpip_fingerprint.py
djspoofer/management/commands/incolumitas_tls_fingerprint.py
djspoofer/management/commands/intoli_get_profiles.py
djspoofer/management/commands/ja3er_details.py
djspoofer/managers.py
djspoofer/migrations/0001_initial.py
djspoofer/migrations/0002_alter_proxy_url.py
djspoofer/migrations/0003_auto_20220506_2242.py
djspoofer/migrations/0004_h2fingerprint_priority_frames.py
djspoofer/migrations/0005_auto_20220515_2315.py
djspoofer/migrations/0006_auto_20220515_2357.py
djspoofer/migrations/0007_alter_h2fingerprint_header_table_size.py
djspoofer/migrations/__init__.py
djspoofer/models.py
djspoofer/providers.py
djspoofer/remote/__init__.py
djspoofer/remote/h2fingerprint/__init__.py
djspoofer/remote/h2fingerprint/exceptions.py
djspoofer/remote/h2fingerprint/h2fingerprint_api.py
djspoofer/remote/howsmyssl/__init__.py
djspoofer/remote/howsmyssl/exceptions.py
djspoofer/remote/howsmyssl/howsmyssl_api.py
djspoofer/remote/incolumitas/__init__.py
djspoofer/remote/incolumitas/exceptions.py
djspoofer/remote/incolumitas/incolumitas_api.py
dj_spoofer-0.1.6.dist-info/LICENSE
dj_spoofer-0.1.6.dist-info/WHEEL
dj_spoofer-0.1.6.dist-info/METADATA
dj_spoofer-0.1.6.dist-info/RECORD
